davinci_rest/__init__.py
davinci_rest/captions.cp312-win_amd64.pyd
davinci_rest/client.py
davinci_rest/davinci_lib.cp312-win_amd64.pyd
davinci_rest/endpoints.cp312-win_amd64.pyd
davinci_rest/launch_davinci_rest.py
davinci_rest/media.cp312-win_amd64.pyd
davinci_rest/server.cp312-win_amd64.pyd
davinci_rest/shortfactory.cp312-win_amd64.pyd
davinci_rest/transi.cp312-win_amd64.pyd
davinci_rest/tts.cp312-win_amd64.pyd
davinci_rest/video_editor.cp312-win_amd64.pyd
davinci_rest/templates/shortfabrik.drp
davinci_rest/templates/shortfabrik_modern_fonts.drp
davinci_rest/templates/shortfactory.drp
davinci_rest-0.2.5.dist-info/licenses/LICENSE
davinci_rest-0.2.5.dist-info/METADATA
davinci_rest-0.2.5.dist-info/WHEEL
davinci_rest-0.2.5.dist-info/top_level.txt
davinci_rest-0.2.5.dist-info/RECORD
