Metadata-Version: 2.4
Name: davinci-rest
Version: 0.2.5
Summary: A REST server for interacting with DaVinci Resolve
Author: Davinci Rest Team
Author-email: davinci-rest@beluck.net
Project-URL: Homepage, https://beluck.net/davinci-rest
Project-URL: YouTube, https://www.youtube.com/@davinci-rest
Project-URL: Bug Reports, https://github.com/dev-beluck/davinci-rest/issues
Project-URL: Documentation, https://beluck.net/davinci-rest#documentation
Project-URL: Source, https://github.com/dev-beluck/davinci-rest
Classifier: Programming Language :: Python :: 3
Classifier: Operating System :: Microsoft :: Windows
Classifier: License :: OSI Approved :: MIT License
Requires-Python: >=3.10
License-File: LICENSE
Requires-Dist: requests
Requires-Dist: fastapi
Requires-Dist: pydantic
Requires-Dist: uvicorn[standard]
Requires-Dist: platformdirs
Requires-Dist: python-multipart
Provides-Extra: audio
Requires-Dist: pydub; extra == "audio"
Provides-Extra: tts-edge
Requires-Dist: edge-tts; extra == "tts-edge"
Provides-Extra: tts-elevenlabs
Requires-Dist: elevenlabs; extra == "tts-elevenlabs"
Provides-Extra: transcription
Requires-Dist: stable-ts; extra == "transcription"
Provides-Extra: all
Requires-Dist: pydub; extra == "all"
Requires-Dist: edge-tts; extra == "all"
Requires-Dist: elevenlabs; extra == "all"
Requires-Dist: stable-ts; extra == "all"
Dynamic: author
Dynamic: author-email
Dynamic: classifier
Dynamic: description
Dynamic: description-content-type
Dynamic: license-file
Dynamic: project-url
Dynamic: provides-extra
Dynamic: requires-dist
Dynamic: requires-python
Dynamic: summary
